Socket_Singleton.py
socket_singleton-2.0.0.dist-info/licenses/LICENSE.txt
socket_singleton-2.0.0.dist-info/METADATA
socket_singleton-2.0.0.dist-info/WHEEL
socket_singleton-2.0.0.dist-info/top_level.txt
socket_singleton-2.0.0.dist-info/RECORD
